lab3_20_rgb_pwm/src/pwm_channel.v
`timescale 1ns/1ps

module pwm_channel #(
parameter integer PERIOD_CYCLES=50_000,
LEVELS=10
) (
input wire clk,
rst_p,
input wire [3:0] level,
output reg pwm
);
localparam integer W=(PERIOD_CYCLES<2)?1:$clog2(PERIOD_CYCLES);
reg [W-1:0] count;
integer threshold;

always @* threshold=(level>=LEVELS)?PERIOD_CYCLES:(PERIOD_CYCLES*level)/LEVELS;

always @(posedge clk or posedge rst_p) if(rst_p) begin
    count<=0;
    pwm<=0;
end
else begin
    pwm<=count<threshold;
    if(count==PERIOD_CYCLES-1)count<=0;
    else count<=count+1'b1;
end

endmodule

lab3_20_rgb_pwm/src/button_onepulse.v
`timescale 1ns/1ps

module button_onepulse #(
parameter integer STABLE_CYCLES=1_000_000
) (
input wire clk,
rst_p,
button,
output reg pulse
);
(* ASYNC_REG="TRUE" *) reg button_meta,button_sync;
localparam integer W=(STABLE_CYCLES<2)?1:$clog2(STABLE_CYCLES);
reg [W-1:0] c;
reg accepted;

always @(posedge clk or posedge rst_p) if(rst_p) begin
    button_meta<=0;
    button_sync<=0;
end
else begin
    button_meta<=button;
    button_sync<=button_meta;
end

always @(posedge clk or posedge rst_p) if(rst_p) begin
    c<=0;
    accepted<=0;
    pulse<=0;
end
else begin
    pulse<=0;
    if(button_sync==accepted)c<=0;
    else if(c==STABLE_CYCLES-1)begin
        c<=0;
        accepted<=button_sync;
        pulse<=button_sync;
    end
    else c<=c+1'b1;
end

endmodule

lab3_20_rgb_pwm/src/lab3_rgb_pwm.v
`timescale 1ns/1ps

module lab3_rgb_pwm #(
parameter integer CLK_HZ=50_000_000,
PWM_HZ=1_000,
LEVELS=10,
DEBOUNCE_CYCLES=1_000_000
) (
input wire clk_50mhz,
rst_p,
button_r,
button_g,
button_b,
output wire [3:0] led_r,
led_g,
led_b
);
wire pr,pg,pb,wr,wg,wb;
reg [3:0] lr,lg,lb;
button_onepulse #(.STABLE_CYCLES(DEBOUNCE_CYCLES)) br(.clk(clk_50mhz),.rst_p(rst_p),.button(button_r),.pulse(pr));
button_onepulse #(.STABLE_CYCLES(DEBOUNCE_CYCLES)) bg(.clk(clk_50mhz),.rst_p(rst_p),.button(button_g),.pulse(pg));
button_onepulse #(.STABLE_CYCLES(DEBOUNCE_CYCLES)) bb(.clk(clk_50mhz),.rst_p(rst_p),.button(button_b),.pulse(pb));

always @(posedge clk_50mhz or posedge rst_p) if(rst_p)begin
    lr<=0;
    lg<=0;
    lb<=0;
end
else begin
    if(pr)lr<=(lr==LEVELS)?0:lr+1'b1;
    if(pg)lg<=(lg==LEVELS)?0:lg+1'b1;
    if(pb)lb<=(lb==LEVELS)?0:lb+1'b1;
end
pwm_channel #(.PERIOD_CYCLES(CLK_HZ/PWM_HZ),.LEVELS(LEVELS)) r(.clk(clk_50mhz),.rst_p(rst_p),.level(lr),.pwm(wr));
pwm_channel #(.PERIOD_CYCLES(CLK_HZ/PWM_HZ),.LEVELS(LEVELS)) g(.clk(clk_50mhz),.rst_p(rst_p),.level(lg),.pwm(wg));
pwm_channel #(.PERIOD_CYCLES(CLK_HZ/PWM_HZ),.LEVELS(LEVELS)) b(.clk(clk_50mhz),.rst_p(rst_p),.level(lb),.pwm(wb));
assign led_r={4{wr}};
assign led_g={4{wg}};
assign led_b={4{wb}};
endmodule

lab3_20_rgb_pwm/sim/tb_rgb_pwm.sv
`timescale 1ns/1ps

module tb_rgb_pwm;
reg clk_50mhz=0,rst_p=1,button_r=0,button_g=0,button_b=0;
wire[3:0]led_r,led_g,led_b;
integer checks=0,i,hr,hg,hb;

always #10 clk_50mhz=~clk_50mhz;
lab3_rgb_pwm #(.CLK_HZ(1000),.PWM_HZ(100),.LEVELS(10),.DEBOUNCE_CYCLES(2))dut(.clk_50mhz(clk_50mhz),.rst_p(rst_p),.button_r(button_r),.button_g(button_g),.button_b(button_b),.led_r(led_r),.led_g(led_g),.led_b(led_b));

task pr;
begin
    button_r=1;
    repeat(6)@(posedge clk_50mhz);
    button_r=0;
    repeat(6)@(posedge clk_50mhz);
end
endtask task pg;
begin
    button_g=1;
    repeat(6)@(posedge clk_50mhz);
    button_g=0;
    repeat(6)@(posedge clk_50mhz);
end
endtask task pb;
begin
    button_b=1;
    repeat(6)@(posedge clk_50mhz);
    button_b=0;
    repeat(6)@(posedge clk_50mhz);
end
endtask task measure(input integer a,b,c);
begin
    wait(dut.r.count==0);
    hr=0;
    hg=0;
    hb=0;
    for(i=0;i<10;i=i+1)begin
        @(posedge clk_50mhz);
        #1;
        hr=hr+led_r[0];
        hg=hg+led_g[0];
        hb=hb+led_b[0];
    end
    if(hr!==a||hg!==b||hb!==c)$fatal(1);
    checks=checks+1;
end
endtask initial begin
    $dumpfile("wave.vcd");
    $dumpvars(0,tb_rgb_pwm);
    repeat(3)@(posedge clk_50mhz);
    rst_p=0;
    repeat(2)pr;
    repeat(5)pg;
    repeat(8)pb;
    measure(2,5,8);
    pr;
    measure(3,5,8);
    $display("LAB3_RGB_PWM_PASS checks=%0d",checks);
    $finish;
end

initial begin
    #30000;
    $fatal(1,"timeout");
end

endmodule

lab3_20_rgb_pwm/evidence/02/vscode/wave.vcd
$date
	Fri Sep 25 22:02:40 2026
$end
$version
	Icarus Verilog
$end
$timescale
	1ps
$end
$scope module tb_rgb_pwm $end
$var wire 4 ! led_r [3:0] $end
$var wire 4 " led_g [3:0] $end
$var wire 4 # led_b [3:0] $end
$var reg 1 $ button_b $end
$var reg 1 % button_g $end
$var reg 1 & button_r $end
$var reg 1 ' clk_50mhz $end
$var reg 1 ( rst_p $end
$var integer 32 ) checks [31:0] $end
$var integer 32 * hb [31:0] $end
$var integer 32 + hg [31:0] $end
$var integer 32 , hr [31:0] $end
$var integer 32 - i [31:0] $end
$scope module dut $end
$var wire 1 $ button_b $end
$var wire 1 % button_g $end
$var wire 1 & button_r $end
$var wire 1 ' clk_50mhz $end
$var wire 1 ( rst_p $end
$var wire 1 . wr $end
$var wire 1 / wg $end
$var wire 1 0 wb $end
$var wire 1 1 pr $end
$var wire 1 2 pg $end
$var wire 1 3 pb $end
$var wire 4 4 led_r [3:0] $end
$var wire 4 5 led_g [3:0] $end
$var wire 4 6 led_b [3:0] $end
$var parameter 32 7 CLK_HZ $end
$var parameter 32 8 DEBOUNCE_CYCLES $end
$var parameter 32 9 LEVELS $end
$var parameter 32 : PWM_HZ $end
$var reg 4 ; lb [3:0] $end
$var reg 4 < lg [3:0] $end
$var reg 4 = lr [3:0] $end
$scope module b $end
$var wire 1 ' clk $end
$var wire 4 > level [3:0] $end
$var wire 1 ( rst_p $end
$var parameter 32 ? LEVELS $end
$var parameter 32 @ PERIOD_CYCLES $end
$var parameter 32 A W $end
$var reg 4 B count [3:0] $end
$var reg 1 0 pwm $end
$var integer 32 C threshold [31:0] $end
$upscope $end
$scope module bb $end
$var wire 1 $ button $end
$var wire 1 ' clk $end
$var wire 1 ( rst_p $end
$var parameter 32 D STABLE_CYCLES $end
$var parameter 32 E W $end
$var reg 1 F accepted $end
$var reg 1 G button_meta $end
$var reg 1 H button_sync $end
$var reg 1 I c $end
$var reg 1 3 pulse $end
$upscope $end
$scope module bg $end
$var wire 1 % button $end
$var wire 1 ' clk $end
$var wire 1 ( rst_p $end
$var parameter 32 J STABLE_CYCLES $end
$var parameter 32 K W $end
$var reg 1 L accepted $end
$var reg 1 M button_meta $end
$var reg 1 N button_sync $end
$var reg 1 O c $end
$var reg 1 2 pulse $end
$upscope $end
$scope module br $end
$var wire 1 & button $end
$var wire 1 ' clk $end
$var wire 1 ( rst_p $end
$var parameter 32 P STABLE_CYCLES $end
$var parameter 32 Q W $end
$var reg 1 R accepted $end
$var reg 1 S button_meta $end
$var reg 1 T button_sync $end
$var reg 1 U c $end
$var reg 1 1 pulse $end
$upscope $end
$scope module g $end
$var wire 1 ' clk $end
$var wire 4 V level [3:0] $end
$var wire 1 ( rst_p $end
$var parameter 32 W LEVELS $end
$var parameter 32 X PERIOD_CYCLES $end
$var parameter 32 Y W $end
$var reg 4 Z count [3:0] $end
$var reg 1 / pwm $end
$var integer 32 [ threshold [31:0] $end
$upscope $end
$scope module r $end
$var wire 1 ' clk $end
$var wire 4 \ level [3:0] $end
$var wire 1 ( rst_p $end
$var parameter 32 ] LEVELS $end
$var parameter 32 ^ PERIOD_CYCLES $end
$var parameter 32 _ W $end
$var reg 4 ` count [3:0] $end
$var reg 1 . pwm $end
$var integer 32 a threshold [31:0] $end
$upscope $end
$upscope $end
$scope task measure $end
$var integer 32 b a [31:0] $end
$var integer 32 c b [31:0] $end
$var integer 32 d c [31:0] $end
$upscope $end
$scope task pb $end
$upscope $end
$scope task pg $end
$upscope $end
$scope task pr $end
$upscope $end
$upscope $end
$enddefinitions $end
$comment Show the parameter values. $end
$dumpall
b100 _
b1010 ^
b1010 ]
b100 Y
b1010 X
b1010 W
b1 Q
b10 P
b1 K
b10 J
b1 E
b10 D
b100 A
b1010 @
b1010 ?
b1100100 :
b1010 9
b10 8
b1111101000 7
$end
#0
$dumpvars
bx d
bx c
bx b
bx a
bx `
bx \
bx [
bx Z
bx V
xU
xT
xS
xR
xO
xN
xM
xL
xI
xH
xG
xF
bx C
bx B
bx >
bx =
bx <
bx ;
bx 6
bx 5
bx 4
x3
x2
x1
x0
x/
x.
bx -
bx ,
bx +
bx *
b0 )
1(
0'
0&
0%
0$
bx #
bx "
bx !
$end
#10000
b0 C
b0 [
b0 a
0T
0S
01
0R
0U
0N
0M
02
0L
0O
0H
0G
03
0F
0I
b0 !
b0 4
0.
b0 `
b0 "
b0 5
0/
b0 Z
b0 #
b0 6
00
b0 B
b0 ;
b0 >
b0 <
b0 V
b0 =
b0 \
1'
#20000
0'
#30000
1'
#40000
0'
#50000
1S
b1 `
b1 Z
b1 B
1&
0(
1'
#60000
0'
#70000
b10 B
b10 Z
b10 `
1T
1'
#80000
0'
#90000
1U
b11 `
b11 Z
b11 B
1'
#100000
0'
#110000
b100 B
b100 Z
b100 `
11
1R
0U
1'
#120000
0'
#130000
b1 a
01
b101 `
b101 Z
b101 B
b1 =
b1 \
1'
#140000
0'
#150000
b110 B
b110 Z
b110 `
1'
#160000
0'
#170000
0S
b111 `
b111 Z
b111 B
0&
1'
#180000
0'
#190000
b1000 B
b1000 Z
b1000 `
0T
1'
#200000
0'
#210000
1U
b1001 `
b1001 Z
b1001 B
1'
#220000
0'
#230000
b0 B
b0 Z
b0 `
0R
0U
1'
#240000
0'
#250000
b1 `
b1111 !
b1111 4
1.
b1 Z
b1 B
1'
#260000
0'
#270000
b10 B
b10 Z
b10 `
b0 !
b0 4
0.
1'
#280000
0'
#290000
1S
b11 `
b11 Z
b11 B
1&
1'
#300000
0'
#310000
b100 B
b100 Z
b100 `
1T
1'
#320000
0'
#330000
1U
b101 `
b101 Z
b101 B
1'
#340000
0'
#350000
b110 B
b110 Z
b110 `
11
1R
0U
1'
#360000
0'
#370000
b10 a
01
b111 `
b111 Z
b111 B
b10 =
b10 \
1'
#380000
0'
#390000
b1000 B
b1000 Z
b1000 `
1'
#400000
0'
#410000
0S
b1001 `
b1001 Z
b1001 B
0&
1'
#420000
0'
#430000
b0 B
b0 Z
b0 `
0T
1'
#440000
0'
#450000
1U
b1 `
b1111 !
b1111 4
1.
b1 Z
b1 B
1'
#460000
0'
#470000
b10 B
b10 Z
b10 `
0R
0U
1'
#480000
0'
#490000
b11 `
b0 !
b0 4
0.
b11 Z
b11 B
1'
#500000
0'
#510000
b100 B
b100 Z
b100 `
1'
#520000
0'
#530000
1M
b101 `
b101 Z
b101 B
1%
1'
#540000
0'
#550000
b110 B
b110 Z
b110 `
1N
1'
#560000
0'
#570000
1O
b111 `
b111 Z
b111 B
1'
#580000
0'
#590000
b1000 B
b1000 Z
b1000 `
12
1L
0O
1'
#600000
0'
#610000
b1 [
02
b1001 `
b1001 Z
b1001 B
b1 <
b1 V
1'
#620000
0'
#630000
b0 B
b0 Z
b0 `
1'
#640000
0'
#650000
0M
b1 `
b1111 !
b1111 4
1.
b1 Z
b1111 "
b1111 5
1/
b1 B
0%
1'
#660000
0'
#670000
b10 B
b10 Z
b0 "
b0 5
0/
b10 `
0N
1'
#680000
0'
#690000
1O
b11 `
b0 !
b0 4
0.
b11 Z
b11 B
1'
#700000
0'
#710000
b100 B
b100 Z
b100 `
0L
0O
1'
#720000
0'
#730000
b101 `
b101 Z
b101 B
1'
#740000
0'
#750000
b110 B
b110 Z
b110 `
1'
#760000
0'
#770000
1M
b111 `
b111 Z
b111 B
1%
1'
#780000
0'
#790000
b1000 B
b1000 Z
b1000 `
1N
1'
#800000
0'
#810000
1O
b1001 `
b1001 Z
b1001 B
1'
#820000
0'
#830000
b0 B
b0 Z
b0 `
12
1L
0O
1'
#840000
0'
#850000
b10 [
02
b1 `
b1111 !
b1111 4
1.
b1 Z
b1111 "
b1111 5
1/
b1 B
b10 <
b10 V
1'
#860000
0'
#870000
b10 B
b10 Z
b10 `
1'
#880000
0'
#890000
0M
b11 `
b0 !
b0 4
0.
b11 Z
b0 "
b0 5
0/
b11 B
0%
1'
#900000
0'
#910000
b100 B
b100 Z
b100 `
0N
1'
#920000
0'
#930000
1O
b101 `
b101 Z
b101 B
1'
#940000
0'
#950000
b110 B
b110 Z
b110 `
0L
0O
1'
#960000
0'
#970000
b111 `
b111 Z
b111 B
1'
#980000
0'
#990000
b1000 B
b1000 Z
b1000 `
1'
#1000000
0'
#1010000
1M
b1001 `
b1001 Z
b1001 B
1%
1'
#1020000
0'
#1030000
b0 B
b0 Z
b0 `
1N
1'
#1040000
0'
#1050000
1O
b1 `
b1111 !
b1111 4
1.
b1 Z
b1111 "
b1111 5
1/
b1 B
1'
#1060000
0'
#1070000
b10 B
b10 Z
b10 `
12
1L
0O
1'
#1080000
0'
#1090000
b11 [
02
b11 `
b0 !
b0 4
0.
b11 Z
b0 "
b0 5
0/
b11 B
b11 <
b11 V
1'
#1100000
0'
#1110000
b100 B
b100 Z
b100 `
1'
#1120000
0'
#1130000
0M
b101 `
b101 Z
b101 B
0%
1'
#1140000
0'
#1150000
b110 B
b110 Z
b110 `
0N
1'
#1160000
0'
#1170000
1O
b111 `
b111 Z
b111 B
1'
#1180000
0'
#1190000
b1000 B
b1000 Z
b1000 `
0L
0O
1'
#1200000
0'
#1210000
b1001 `
b1001 Z
b1001 B
1'
#1220000
0'
#1230000
b0 B
b0 Z
b0 `
1'
#1240000
0'
#1250000
1M
b1 `
b1111 !
b1111 4
1.
b1 Z
b1111 "
b1111 5
1/
b1 B
1%
1'
#1260000
0'
#1270000
b10 B
b10 Z
b10 `
1N
1'
#1280000
0'
#1290000
1O
b11 `
b0 !
b0 4
0.
b11 Z
b11 B
1'
#1300000
0'
#1310000
b100 B
b100 Z
b0 "
b0 5
0/
b100 `
12
1L
0O
1'
#1320000
0'
#1330000
b100 [
02
b101 `
b101 Z
b101 B
b100 <
b100 V
1'
#1340000
0'
#1350000
b110 B
b110 Z
b110 `
1'
#1360000
0'
#1370000
0M
b111 `
b111 Z
b111 B
0%
1'
#1380000
0'
#1390000
b1000 B
b1000 Z
b1000 `
0N
1'
#1400000
0'
#1410000
1O
b1001 `
b1001 Z
b1001 B
1'
#1420000
0'
#1430000
b0 B
b0 Z
b0 `
0L
0O
1'
#1440000
0'
#1450000
b1 `
b1111 !
b1111 4
1.
b1 Z
b1111 "
b1111 5
1/
b1 B
1'
#1460000
0'
#1470000
b10 B
b10 Z
b10 `
1'
#1480000
0'
#1490000
1M
b11 `
b0 !
b0 4
0.
b11 Z
b11 B
1%
1'
#1500000
0'
#1510000
b100 B
b100 Z
b100 `
1N
1'
#1520000
0'
#1530000
1O
b101 `
b101 Z
b0 "
b0 5
0/
b101 B
1'
#1540000
0'
#1550000
b110 B
b110 Z
b110 `
12
1L
0O
1'
#1560000
0'
#1570000
b101 [
02
b111 `
b111 Z
b111 B
b101 <
b101 V
1'
#1580000
0'
#1590000
b1000 B
b1000 Z
b1000 `
1'
#1600000
0'
#1610000
0M
b1001 `
b1001 Z
b1001 B
0%
1'
#1620000
0'
#1630000
b0 B
b0 Z
b0 `
0N
1'
#1640000
0'
#1650000
1O
b1 `
b1111 !
b1111 4
1.
b1 Z
b1111 "
b1111 5
1/
b1 B
1'
#1660000
0'
#1670000
b10 B
b10 Z
b10 `
0L
0O
1'
#1680000
0'
#1690000
b11 `
b0 !
b0 4
0.
b11 Z
b11 B
1'
#1700000
0'
#1710000
b100 B
b100 Z
b100 `
1'
#1720000
0'
#1730000
1G
b101 `
b101 Z
b101 B
1$
1'
#1740000
0'
#1750000
b110 B
b110 Z
b0 "
b0 5
0/
b110 `
1H
1'
#1760000
0'
#1770000
1I
b111 `
b111 Z
b111 B
1'
#1780000
0'
#1790000
b1000 B
b1000 Z
b1000 `
13
1F
0I
1'
#1800000
0'
#1810000
b1 C
03
b1001 `
b1001 Z
b1001 B
b1 ;
b1 >
1'
#1820000
0'
#1830000
b0 B
b0 Z
b0 `
1'
#1840000
0'
#1850000
0G
b1 `
b1111 !
b1111 4
1.
b1 Z
b1111 "
b1111 5
1/
b1 B
b1111 #
b1111 6
10
0$
1'
#1860000
0'
#1870000
b10 B
b0 #
b0 6
00
b10 Z
b10 `
0H
1'
#1880000
0'
#1890000
1I
b11 `
b0 !
b0 4
0.
b11 Z
b11 B
1'
#1900000
0'
#1910000
b100 B
b100 Z
b100 `
0F
0I
1'
#1920000
0'
#1930000
b101 `
b101 Z
b101 B
1'
#1940000
0'
#1950000
b110 B
b110 Z
b0 "
b0 5
0/
b110 `
1'
#1960000
0'
#1970000
1G
b111 `
b111 Z
b111 B
1$
1'
#1980000
0'
#1990000
b1000 B
b1000 Z
b1000 `
1H
1'
#2000000
0'
#2010000
1I
b1001 `
b1001 Z
b1001 B
1'
#2020000
0'
#2030000
b0 B
b0 Z
b0 `
13
1F
0I
1'
#2040000
0'
#2050000
b10 C
03
b1 `
b1111 !
b1111 4
1.
b1 Z
b1111 "
b1111 5
1/
b1 B
b1111 #
b1111 6
10
b10 ;
b10 >
1'
#2060000
0'
#2070000
b10 B
b10 Z
b10 `
1'
#2080000
0'
#2090000
0G
b11 `
b0 !
b0 4
0.
b11 Z
b11 B
b0 #
b0 6
00
0$
1'
#2100000
0'
#2110000
b100 B
b100 Z
b100 `
0H
1'
#2120000
0'
#2130000
1I
b101 `
b101 Z
b101 B
1'
#2140000
0'
#2150000
b110 B
b110 Z
b0 "
b0 5
0/
b110 `
0F
0I
1'
#2160000
0'
#2170000
b111 `
b111 Z
b111 B
1'
#2180000
0'
#2190000
b1000 B
b1000 Z
b1000 `
1'
#2200000
0'
#2210000
1G
b1001 `
b1001 Z
b1001 B
1$
1'
#2220000
0'
#2230000
b0 B
b0 Z
b0 `
1H
1'
#2240000
0'
#2250000
1I
b1 `
b1111 !
b1111 4
1.
b1 Z
b1111 "
b1111 5
1/
b1 B
b1111 #
b1111 6
10
1'
#2260000
0'
#2270000
b10 B
b10 Z
b10 `
13
1F
0I
1'
#2280000
0'
#2290000
b11 C
03
b11 `
b0 !
b0 4
0.
b11 Z
b11 B
b0 #
b0 6
00
b11 ;
b11 >
1'
#2300000
0'
#2310000
b100 B
b100 Z
b100 `
1'
#2320000
0'
#2330000
0G
b101 `
b101 Z
b101 B
0$
1'
#2340000
0'
#2350000
b110 B
b110 Z
b0 "
b0 5
0/
b110 `
0H
1'
#2360000
0'
#2370000
1I
b111 `
b111 Z
b111 B
1'
#2380000
0'
#2390000
b1000 B
b1000 Z
b1000 `
0F
0I
1'
#2400000
0'
#2410000
b1001 `
b1001 Z
b1001 B
1'
#2420000
0'
#2430000
b0 B
b0 Z
b0 `
1'
#2440000
0'
#2450000
1G
b1 `
b1111 !
b1111 4
1.
b1 Z
b1111 "
b1111 5
1/
b1 B
b1111 #
b1111 6
10
1$
1'
#2460000
0'
#2470000
b10 B
b10 Z
b10 `
1H
1'
#2480000
0'
#2490000
1I
b11 `
b0 !
b0 4
0.
b11 Z
b11 B
1'
#2500000
0'
#2510000
b100 B
b0 #
b0 6
00
b100 Z
b100 `
13
1F
0I
1'
#2520000
0'
#2530000
b100 C
03
b101 `
b101 Z
b101 B
b100 ;
b100 >
1'
#2540000
0'
#2550000
b110 B
b110 Z
b0 "
b0 5
0/
b110 `
1'
#2560000
0'
#2570000
0G
b111 `
b111 Z
b111 B
0$
1'
#2580000
0'
#2590000
b1000 B
b1000 Z
b1000 `
0H
1'
#2600000
0'
#2610000
1I
b1001 `
b1001 Z
b1001 B
1'
#2620000
0'
#2630000
b0 B
b0 Z
b0 `
0F
0I
1'
#2640000
0'
#2650000
b1 `
b1111 !
b1111 4
1.
b1 Z
b1111 "
b1111 5
1/
b1 B
b1111 #
b1111 6
10
1'
#2660000
0'
#2670000
b10 B
b10 Z
b10 `
1'
#2680000
0'
#2690000
1G
b11 `
b0 !
b0 4
0.
b11 Z
b11 B
1$
1'
#2700000
0'
#2710000
b100 B
b100 Z
b100 `
1H
1'
#2720000
0'
#2730000
1I
b101 `
b101 Z
b101 B
b0 #
b0 6
00
1'
#2740000
0'
#2750000
b110 B
b110 Z
b0 "
b0 5
0/
b110 `
13
1F
0I
1'
#2760000
0'
#2770000
b101 C
03
b111 `
b111 Z
b111 B
b101 ;
b101 >
1'
#2780000
0'
#2790000
b1000 B
b1000 Z
b1000 `
1'
#2800000
0'
#2810000
0G
b1001 `
b1001 Z
b1001 B
0$
1'
#2820000
0'
#2830000
b0 B
b0 Z
b0 `
0H
1'
#2840000
0'
#2850000
1I
b1 `
b1111 !
b1111 4
1.
b1 Z
b1111 "
b1111 5
1/
b1 B
b1111 #
b1111 6
10
1'
#2860000
0'
#2870000
b10 B
b10 Z
b10 `
0F
0I
1'
#2880000
0'
#2890000
b11 `
b0 !
b0 4
0.
b11 Z
b11 B
1'
#2900000
0'
#2910000
b100 B
b100 Z
b100 `
1'
#2920000
0'
#2930000
1G
b101 `
b101 Z
b101 B
1$
1'
#2940000
0'
#2950000
b110 B
b0 #
b0 6
00
b110 Z
b0 "
b0 5
0/
b110 `
1H
1'
#2960000
0'
#2970000
1I
b111 `
b111 Z
b111 B
1'
#2980000
0'
#2990000
b1000 B
b1000 Z
b1000 `
13
1F
0I
1'
#3000000
0'
#3010000
b110 C
03
b1001 `
b1001 Z
b1001 B
b110 ;
b110 >
1'
#3020000
0'
#3030000
b0 B
b0 Z
b0 `
1'
#3040000
0'
#3050000
0G
b1 `
b1111 !
b1111 4
1.
b1 Z
b1111 "
b1111 5
1/
b1 B
b1111 #
b1111 6
10
0$
1'
#3060000
0'
#3070000
b10 B
b10 Z
b10 `
0H
1'
#3080000
0'
#3090000
1I
b11 `
b0 !
b0 4
0.
b11 Z
b11 B
1'
#3100000
0'
#3110000
b100 B
b100 Z
b100 `
0F
0I
1'
#3120000
0'
#3130000
b101 `
b101 Z
b101 B
1'
#3140000
0'
#3150000
b110 B
b110 Z
b0 "
b0 5
0/
b110 `
1'
#3160000
0'
#3170000
1G
b111 `
b111 Z
b111 B
b0 #
b0 6
00
1$
1'
#3180000
0'
#3190000
b1000 B
b1000 Z
b1000 `
1H
1'
#3200000
0'
#3210000
1I
b1001 `
b1001 Z
b1001 B
1'
#3220000
0'
#3230000
b0 B
b0 Z
b0 `
13
1F
0I
1'
#3240000
0'
#3250000
b111 C
03
b1 `
b1111 !
b1111 4
1.
b1 Z
b1111 "
b1111 5
1/
b1 B
b1111 #
b1111 6
10
b111 ;
b111 >
1'
#3260000
0'
#3270000
b10 B
b10 Z
b10 `
1'
#3280000
0'
#3290000
0G
b11 `
b0 !
b0 4
0.
b11 Z
b11 B
0$
1'
#3300000
0'
#3310000
b100 B
b100 Z
b100 `
0H
1'
#3320000
0'
#3330000
1I
b101 `
b101 Z
b101 B
1'
#3340000
0'
#3350000
b110 B
b110 Z
b0 "
b0 5
0/
b110 `
0F
0I
1'
#3360000
0'
#3370000
b111 `
b111 Z
b111 B
1'
#3380000
0'
#3390000
b1000 B
b0 #
b0 6
00
b1000 Z
b1000 `
1'
#3400000
0'
#3410000
1G
b1001 `
b1001 Z
b1001 B
1$
1'
#3420000
0'
#3430000
b0 B
b0 Z
b0 `
1H
1'
#3440000
0'
#3450000
1I
b1 `
b1111 !
b1111 4
1.
b1 Z
b1111 "
b1111 5
1/
b1 B
b1111 #
b1111 6
10
1'
#3460000
0'
#3470000
b10 B
b10 Z
b10 `
13
1F
0I
1'
#3480000
0'
#3490000
b1000 C
03
b11 `
b0 !
b0 4
0.
b11 Z
b11 B
b1000 ;
b1000 >
1'
#3500000
0'
#3510000
b100 B
b100 Z
b100 `
1'
#3520000
0'
#3530000
0G
b101 `
b101 Z
b101 B
0$
1'
#3540000
0'
#3550000
b110 B
b110 Z
b0 "
b0 5
0/
b110 `
0H
1'
#3560000
0'
#3570000
1I
b111 `
b111 Z
b111 B
1'
#3580000
0'
#3590000
b1000 B
b1000 Z
b1000 `
0F
0I
1'
#3600000
0'
#3610000
b1001 `
b1001 Z
b1001 B
b0 #
b0 6
00
1'
#3620000
0'
#3630000
b0 B
b0 Z
b0 `
1'
#3640000
0'
#3650000
b1 `
b1111 !
b1111 4
1.
b1 Z
b1111 "
b1111 5
1/
b1 B
b1111 #
b1111 6
10
b0 -
b0 *
b0 +
b0 ,
b1000 d
b101 c
b10 b
1'
#3660000
0'
#3670000
b10 B
b10 Z
b10 `
1'
#3671000
b1 -
b1 *
b1 +
b1 ,
#3680000
0'
#3690000
b11 `
b0 !
b0 4
0.
b11 Z
b11 B
1'
#3691000
b10 -
b10 *
b10 +
#3700000
0'
#3710000
b100 B
b100 Z
b100 `
1'
#3711000
b11 -
b11 *
b11 +
#3720000
0'
#3730000
b101 `
b101 Z
b101 B
1'
#3731000
b100 -
b100 *
b100 +
#3740000
0'
#3750000
b110 B
b110 Z
b0 "
b0 5
0/
b110 `
1'
#3751000
b101 -
b101 *
#3760000
0'
#3770000
b111 `
b111 Z
b111 B
1'
#3771000
b110 -
b110 *
#3780000
0'
#3790000
b1000 B
b1000 Z
b1000 `
1'
#3791000
b111 -
b111 *
#3800000
0'
#3810000
b1001 `
b1001 Z
b1001 B
b0 #
b0 6
00
1'
#3811000
b1000 -
#3820000
0'
#3830000
b0 B
b0 Z
b0 `
1'
#3831000
b1001 -
#3840000
0'
#3850000
b1 `
b1111 !
b1111 4
1.
b1 Z
b1111 "
b1111 5
1/
b1 B
b1111 #
b1111 6
10
1'
#3851000
1&
b1 )
b1010 -
b1000 *
b101 +
b10 ,
#3860000
0'
#3870000
b10 B
b10 Z
b10 `
1S
1'
#3880000
0'
#3890000
1T
b11 `
b0 !
b0 4
0.
b11 Z
b11 B
1'
#3900000
0'
#3910000
b100 B
b100 Z
b100 `
1U
1'
#3920000
0'
#3930000
11
1R
0U
b101 `
b101 Z
b101 B
1'
#3940000
0'
#3950000
b11 a
b11 =
b11 \
b110 B
b110 Z
b0 "
b0 5
0/
b110 `
01
1'
#3960000
0'
#3970000
0S
b111 `
b111 Z
b111 B
0&
1'
#3980000
0'
#3990000
b1000 B
b1000 Z
b1000 `
0T
1'
#4000000
0'
#4010000
1U
b1001 `
b1001 Z
b1001 B
b0 #
b0 6
00
1'
#4020000
0'
#4030000
b0 B
b0 Z
b0 `
0R
0U
1'
#4040000
0'
#4050000
b1 `
b1111 !
b1111 4
1.
b1 Z
b1111 "
b1111 5
1/
b1 B
b1111 #
b1111 6
10
1'
#4060000
0'
#4070000
b10 B
b10 Z
b10 `
1'
#4080000
0'
#4090000
b11 `
b11 Z
b11 B
b11 b
1'
#4100000
0'
#4110000
b100 B
b100 Z
b100 `
b0 !
b0 4
0.
1'
#4120000
0'
#4130000
b101 `
b101 Z
b101 B
1'
#4140000
0'
#4150000
b110 B
b110 Z
b0 "
b0 5
0/
b110 `
1'
#4160000
0'
#4170000
b111 `
b111 Z
b111 B
1'
#4180000
0'
#4190000
b1000 B
b1000 Z
b1000 `
1'
#4200000
0'
#4210000
b1001 `
b1001 Z
b1001 B
b0 #
b0 6
00
1'
#4220000
0'
#4230000
b0 -
b0 *
b0 +
b0 ,
b0 B
b0 Z
b0 `
1'
#4240000
0'
#4250000
b1 `
b1111 !
b1111 4
1.
b1 Z
b1111 "
b1111 5
1/
b1 B
b1111 #
b1111 6
10
1'
#4251000
b1 -
b1 *
b1 +
b1 ,
#4260000
0'
#4270000
b10 B
b10 Z
b10 `
1'
#4271000
b10 -
b10 *
b10 +
b10 ,
#4280000
0'
#4290000
b11 `
b11 Z
b11 B
1'
#4291000
b11 -
b11 *
b11 +
b11 ,
#4300000
0'
#4310000
b100 B
b100 Z
b100 `
b0 !
b0 4
0.
1'
#4311000
b100 -
b100 *
b100 +
#4320000
0'
#4330000
b101 `
b101 Z
b101 B
1'
#4331000
b101 -
b101 *
b101 +
#4340000
0'
#4350000
b110 B
b110 Z
b0 "
b0 5
0/
b110 `
1'
#4351000
b110 -
b110 *
#4360000
0'
#4370000
b111 `
b111 Z
b111 B
1'
#4371000
b111 -
b111 *
#4380000
0'
#4390000
b1000 B
b1000 Z
b1000 `
1'
#4391000
b1000 -
b1000 *
#4400000
0'
#4410000
b1001 `
b1001 Z
b1001 B
b0 #
b0 6
00
1'
#4411000
b1001 -
#4420000
0'
#4430000
b0 B
b0 Z
b0 `
1'
#4431000
b10 )
b1010 -
